{
    "title" : "Mr.",
    "firstName" : "Godfrey",
    "lastName" : "Block",
    "name" : "Godfrey_Block",
    "password" : "BOPDcSsoOHXCcII",
    "email" : "Godfrey.Block@yopmail.com",
    "dayOfBirth" : "30",
    "monthOfBirth" : "8",
    "yearOfBirth" : "1997",
    "company" : "Emard LLC",
    "address1" : "9531 Koelpin Isle",
    "address2" : "4115",
    "country" : "United States",
    "state" : "Connecticut",
    "city" : "South Elza",
    "zipCode" : "19022",
    "mobileNumber" : "1-474-696-5471 x88540"
    }